{
 "kind": "CubeQueryTableSchema",
 "id": "b4d9d4846e465ee9032dcde77ab494e9e1d5d5c175bd447ab386f351d8229d52",
 "isDeleted": false,
 "rev": "",
 "description": "",
 "name": "row",
 "acl": {
  "kind": "Acl",
  "owner": "",
  "aces": []
 },
 "createdDate": {
  "kind": "Date",
  "value": ""
 },
 "lastModifiedDate": {
  "kind": "Date",
  "value": ""
 },
 "urls": [],
 "tags": [],
 "meta": [
  {
   "kind": "Pair",
   "key": "logicle..channel_description.size_in_bytes",
   "value": "872"
  },
  {
   "kind": "Pair",
   "key": "SHA256",
   "value": "b4d9d4846e465ee9032dcde77ab494e9e1d5d5c175bd447ab386f351d8229d52"
  }
 ],
 "url": {
  "kind": "Url",
  "uri": ""
 },
 "version": "",
 "isPublic": false,
 "projectId": "",
 "folderId": "",
 "nRows": 40,
 "columns": [
  {
   "kind": "ColumnSchema",
   "id": "2e644c7e-ee11-4b91-93fe-93660f077ed9",
   "name": "logicle..channel_description",
   "type": "string",
   "nRows": 0,
   "size": -1,
   "metaData": {
    "kind": "ColumnSchemaMetaData",
    "sort": [],
    "ascending": true,
    "quartiles": [],
    "properties": []
   }
  }
 ],
 "dataDirectory": "data/b4/d9/b4d9d4846e465ee9032dcde77ab494e9e1d5d5c175bd447ab386f351d8229d52",
 "relation": {
  "kind": "Relation",
  "id": "b172de80-2f14-4b7a-8815-a60c5f2e57b3"
 },
 "size": 10120,
 "queryHash": "6e83b855c3350e129a36df256d15fa77",
 "queryTableType": "row",
 "query": {
  "kind": "CubeQuery",
  "relation": {
   "kind": "Relation",
   "id": "0f357b0e-1281-4b93-8f80-654836c50c51"
  },
  "colColumns": [],
  "rowColumns": [],
  "axisQueries": [],
  "filters": {
   "kind": "Filters",
   "removeNaN": true,
   "namedFilters": []
  },
  "operatorSettings": {
   "kind": "OperatorSettings",
   "namespace": "",
   "operatorRef": {
    "kind": "OperatorRef",
    "name": "",
    "version": "",
    "operatorId": "",
    "operatorKind": "",
    "propertyValues": [],
    "url": {
     "kind": "Url",
     "uri": ""
    },
    "operatorSpec": {
     "kind": "OperatorSpec",
     "ontologyUri": "",
     "ontologyVersion": "",
     "inputSpecs": [],
     "outputSpecs": []
    }
   },
   "environment": [],
   "operatorModel": {
    "kind": "OperatorModel"
   }
  },
  "qtHash": "",
  "columnHash": "",
  "rowHash": ""
 }
}